kron.py
kron-1.6.12.dist-info/DESCRIPTION.rst
kron-1.6.12.dist-info/METADATA
kron-1.6.12.dist-info/RECORD
kron-1.6.12.dist-info/WHEEL
kron-1.6.12.dist-info/entry_points.txt
kron-1.6.12.dist-info/metadata.json
kron-1.6.12.dist-info/top_level.txt
