Metadata-Version: 2.0
Name: kron
Version: 1.6.12
Summary: Uniform interface for dates and times
Home-page: https://github.com/qtfkwk/kron
Author: qtfkwk
Author-email: qtfkwk+kron@gmail.com
License: UNKNOWN
Platform: UNKNOWN
Classifier: Development Status :: 5 - Production/Stable
Classifier: Environment :: Console
Classifier: Intended Audience :: Developers
Classifier: Intended Audience :: End Users/Desktop
Classifier: License :: OSI Approved :: BSD License
Classifier: Operating System :: OS Independent
Classifier: Topic :: Utilities
Classifier: Topic :: Software Development :: Libraries :: Python Modules
Classifier: Programming Language :: Python :: 2
Classifier: Programming Language :: Python :: 2.7
Classifier: Programming Language :: Python :: 3
Classifier: Programming Language :: Python :: 3.5
Requires-Dist: future
Requires-Dist: ntplib
Requires-Dist: pytz
Requires-Dist: tzlocal
